{
  "indexes": [
    {
      "collectionGroup": "events",
      "queryScope": "COLLECTION",
      "fields": [
        {
          "fieldPath": "archived",
          "order": "ASCENDING"
        },
        {
          "fieldPath": "dateAdded",
          "order": "ASCENDING"
        }
      ]
    },
    {
      "collectionGroup": "portals",
      "queryScope": "COLLECTION",
      "fields": [
        {
          "fieldPath": "archived",
          "order": "ASCENDING"
        },
        {
          "fieldPath": "dateAdded",
          "order": "ASCENDING"
        }
      ]
    },
    {
      "collectionGroup": "tips",
      "queryScope": "COLLECTION",
      "fields": [
        {
          "fieldPath": "dateAdded",
          "order": "ASCENDING"
        },
        {
          "fieldPath": "archived",
          "order": "ASCENDING"
        }
      ]
    }
  ],
  "fieldOverrides": []
}
